{
    "국내도서": {
        "가정 살림": {
            "임신/출산": ["임신", "태교"],
            "육아": ["성장발달", "건강하게 키우기", "바르게 키우기", "놀이로 키우기", "육아법/육아일기"],
            "자녀교육": [
                "학습법일반", "놀이교육", "독서교육", "영어교육", "감성/체험교육", "영재/지능개발",
                "초등생활지도", "좋은부모되기", "자녀교육일반"
            ],
            "요리": {
                "요리일반": [
                    "요리에세이", "식사예절/매너", "식품과영양", "맛집기행", "맛집기행/국내", "맛집기행/국외"
                ],
                "생활요리": ["기초/간단요리", "가정식탁요리"],
                "개인요리책": ["요리전문가", "연예인", "블로거"],
                "상황별요리": [
                    "이유식", "어린이요리/간식", "건강웰빙요리", "다이어트요리", "초대/명절/파티요리"
                ],
                "메뉴별/나라별요리": [
                    "샌드위치/도시락/면", "샐러드/디저트", "일본요리", "중국요리", "이탈리아요리", "프랑스요리", "기타국가요리"
                ],
                "홈베이킹/베이커리": ["빵/과자/케익", "떡/한과"],
                "한국전통요리": ["차/술/음료", "와인", "커피", "차/다도/음료", "술"]
            },
            "집/살림": [
                "인테리어", "소품", "정리/수납", "살림의지혜", "정원가꾸기", "주거생활"
            ],
            "결혼/가족": ["결혼", "부부관계", "가족관계", "노부모"]
          },
        "건강 취미": [],
        "경제 경영": [],
        "국어 외국어 사전": [],
        "대학교재": [],
        "만화/라이트노벨": [],
        "사회 정치": [],
        "소설/시/희곡": [],
        "수험서 자격증": [],
        "어린이": [],
        "에세이": [],
        "여행": [],
        "역사": [],
        "예술": [],
        "유아": [],
        "인문": [],
        "인물": [],
        "자기계발": [],
        "자연과학": [],
        "잡지": [],
        "전집": [],
        "종교": [],
        "청소년": [],
        "IT 모바일": [],
        "초등참고서": [],
        "중고등참고서": []
    }
}